README.md
setup.py
linkedin_group_joiner_bot/__init__.py
linkedin_group_joiner_bot.egg-info/PKG-INFO
linkedin_group_joiner_bot.egg-info/SOURCES.txt
linkedin_group_joiner_bot.egg-info/dependency_links.txt
linkedin_group_joiner_bot.egg-info/requires.txt
linkedin_group_joiner_bot.egg-info/top_level.txt