Metadata-Version: 2.1
Name: linkedin-group-joiner-bot
Version: 1.0.0
Summary: A python library to join groups on linkedin automatically.
Home-page: https://linkedin-api.datakund.com/en/latest/
Author: DataKund
Author-email: datakund@gmail.com
License: Apache License 2.0
Keywords: linkedin python bot_studio automation join group login
Platform: UNKNOWN
